README.rst
crcelk.py
setup.py
crcelk.egg-info/PKG-INFO
crcelk.egg-info/SOURCES.txt
crcelk.egg-info/dependency_links.txt
crcelk.egg-info/top_level.txt