Metadata-Version: 1.2
Name: crcelk
Version: 1.3
Summary: CrcElk is an updated fork of the CrcMoose module for recent versions of Python. It provides a pure Python implementation of the CRC algorithm and allows for variants to easily be defined by providing their parameters such as width, starting polynomial, etc. Python versions 2.6+ and 3.1+ are supported.
Home-page: https://github.com/zeroSteiner/crcelk
Author: Ray Burr
Maintainer: Spencer McIntyre
Maintainer-email: zeroSteiner@gmail.com
License: MIT
Platform: UNKNOWN
Classifier: Development Status :: 5 - Production/Stable
Classifier: Environment :: Console
Classifier: Intended Audience :: Developers
Classifier: License :: OSI Approved :: MIT License
Classifier: Operating System :: OS Independent
Classifier: Programming Language :: Python :: 2.6
Classifier: Programming Language :: Python :: 2.7
Classifier: Programming Language :: Python :: 3.1
Classifier: Programming Language :: Python :: 3.2
Classifier: Programming Language :: Python :: 3.3
Classifier: Programming Language :: Python :: 3.4
Classifier: Programming Language :: Python :: 3.5
Classifier: Programming Language :: Python :: 3.6
Classifier: Programming Language :: Python :: 3.7
Classifier: Topic :: Software Development :: Libraries :: Python Modules
